[
  {
    "url": "https://casa.mercadolibre.com.ar/MLA-1463603273",
    "fecha": 1733106976410
  },
  {
    "url": "https://casa.mercadolibre.com.ar/MLA-1463524205",
    "fecha": 1733085396723
  },
  {
    "url": "https://casa.mercadolibre.com.ar/MLA-1968790666",
    "fecha": 1733068295660
  },
  {
    "url": "https://casa.mercadolibre.com.ar/MLA-1463393883",
    "fecha": 1733059552501
  },
  {
    "url": "https://casa.mercadolibre.com.ar/MLA-1463445699",
    "fecha": 1733059550883
  },
  {
    "url": "https://casa.mercadolibre.com.ar/MLA-1463413421",
    "fecha": 1733059549012
  },
  {
    "url": "https://departamento.mercadolibre.com.ar/MLA-1967299558",
    "fecha": 1732753363517
  },
  {
    "url": "https://casa.mercadolibre.com.ar/MLA-1462916227",
    "fecha": 1732735082985
  },
  {
    "url": "https://casa.mercadolibre.com.ar/MLA-1462852555",
    "fecha": 1732735081336
  },
  {
    "url": "https://casa.mercadolibre.com.ar/MLA-1462879671",
    "fecha": 1732735079094
  },
  {
    "url": "https://casa.mercadolibre.com.ar/MLA-1966669764",
    "fecha": 1732735077191
  },
  {
    "url": "https://casa.mercadolibre.com.ar/MLA-1966650228",
    "fecha": 1732708332571
  },
  {
    "url": "https://inmueble.mercadolibre.com.ar/MLA-1966611654",
    "fecha": 1732708330749
  },
  {
    "url": "https://inmueble.mercadolibre.com.ar/MLA-1966482046",
    "fecha": 1732708328612
  },
  {
    "url": "https://inmueble.mercadolibre.com.ar/MLA-1966559804",
    "fecha": 1732708327194
  },
  {
    "url": "https://inmueble.mercadolibre.com.ar/MLA-1966611658",
    "fecha": 1732708325117
  },
  {
    "url": "https://casa.mercadolibre.com.ar/MLA-1966481586",
    "fecha": 1732708323137
  },
  {
    "url": "https://casa.mercadolibre.com.ar/MLA-1462758105",
    "fecha": 1732669199928
  },
  {
    "url": "https://terreno.mercadolibre.com.ar/MLA-1462706537",
    "fecha": 1732669198096
  },
  {
    "url": "https://casa.mercadolibre.com.ar/MLA-1966279066",
    "fecha": 1732669195968
  },
  {
    "url": "https://departamento.mercadolibre.com.ar/MLA-1966281410",
    "fecha": 1732669194250
  },
  {
    "url": "https://casa.mercadolibre.com.ar/MLA-1462794481",
    "fecha": 1732643412552
  },
  {
    "url": "https://casa.mercadolibre.com.ar/MLA-1462625521",
    "fecha": 1732643410132
  },
  {
    "url": "https://casa.mercadolibre.com.ar/MLA-1462565021",
    "fecha": 1732643408350
  },
  {
    "url": "https://terreno.mercadolibre.com.ar/MLA-1462568159",
    "fecha": 1732643406405
  },
  {
    "url": "https://casa.mercadolibre.com.ar/MLA-1462589645",
    "fecha": 1732643404563
  },
  {
    "url": "https://casa.mercadolibre.com.ar/MLA-1965629304",
    "fecha": 1732579342361
  },
  {
    "url": "https://casa.mercadolibre.com.ar/MLA-1965704580",
    "fecha": 1732579340288
  },
  {
    "url": "https://casa.mercadolibre.com.ar/MLA-1965159242",
    "fecha": 1732565814592
  },
  {
    "url": "https://casa.mercadolibre.com.ar/MLA-1965172488",
    "fecha": 1732565812761
  },
  {
    "url": "https://inmueble.mercadolibre.com.ar/MLA-1462405141",
    "fecha": 1732565811366
  },
  {
    "url": "https://inmueble.mercadolibre.com.ar/MLA-1964868898",
    "fecha": 1732565809809
  },
  {
    "url": "https://casa.mercadolibre.com.ar/MLA-1965069026",
    "fecha": 1732565807493
  },
  {
    "url": "https://inmueble.mercadolibre.com.ar/MLA-1964909014",
    "fecha": 1732565805787
  },
  {
    "url": "https://casa.mercadolibre.com.ar/MLA-1462363889",
    "fecha": 1732495464198
  },
  {
    "url": "https://casa.mercadolibre.com.ar/MLA-1462375339",
    "fecha": 1732495462088
  },
  {
    "url": "https://terreno.mercadolibre.com.ar/MLA-1964591680",
    "fecha": 1732461265002
  },
  {
    "url": "https://inmueble.mercadolibre.com.ar/MLA-1964637344",
    "fecha": 1732402924572
  },
  {
    "url": "https://terreno.mercadolibre.com.ar/MLA-1462276175",
    "fecha": 1732399340582
  },
  {
    "url": "https://terreno.mercadolibre.com.ar/MLA-1462156293",
    "fecha": 1732399338788
  },
  {
    "url": "https://casa.mercadolibre.com.ar/MLA-1964288304",
    "fecha": 1732381835001
  },
  {
    "url": "https://casa.mercadolibre.com.ar/MLA-1964070442",
    "fecha": 1732381834906
  },
  {
    "url": "https://casa.mercadolibre.com.ar/MLA-1964045620",
    "fecha": 1732381834245
  },
  {
    "url": "https://terreno.mercadolibre.com.ar/MLA-1963489084",
    "fecha": 1732321923081
  },
  {
    "url": "https://casa.mercadolibre.com.ar/MLA-1462074035",
    "fecha": 1732321923060
  },
  {
    "url": "https://terreno.mercadolibre.com.ar/MLA-1963437046",
    "fecha": 1732321923060
  },
  {
    "url": "https://casa.mercadolibre.com.ar/MLA-1964039046",
    "fecha": 1732321923059
  },
  {
    "url": "https://terreno.mercadolibre.com.ar/MLA-1964141660",
    "fecha": 1732321923014
  },
  {
    "url": "https://casa.mercadolibre.com.ar/MLA-1964060952",
    "fecha": 1732321922993
  },
  {
    "url": "https://casa.mercadolibre.com.ar/MLA-1462107793",
    "fecha": 1732321922987
  },
  {
    "url": "https://casa.mercadolibre.com.ar/MLA-1963431442",
    "fecha": 1732321922983
  },
  {
    "url": "https://inmueble.mercadolibre.com.ar/MLA-1462117051",
    "fecha": 1732321922366
  },
  {
    "url": "https://casa.mercadolibre.com.ar/MLA-1962687016",
    "fecha": 1732220142531
  },
  {
    "url": "https://departamento.mercadolibre.com.ar/MLA-1461872245",
    "fecha": 1732220136999
  },
  {
    "url": "https://departamento.mercadolibre.com.ar/MLA-1461887233",
    "fecha": 1732220131923
  },
  {
    "url": "https://departamento.mercadolibre.com.ar/MLA-1962356086",
    "fecha": 1732157284484
  },
  {
    "url": "https://terreno.mercadolibre.com.ar/MLA-1962364018",
    "fecha": 1732157277530
  },
  {
    "url": "https://casa.mercadolibre.com.ar/MLA-1961717988",
    "fecha": 1732117523541
  }
]