[
  {
    "url": "https://terreno.mercadolibre.com.ar/MLA-1968988696",
    "fecha": 1733107285875
  },
  {
    "url": "https://casa.mercadolibre.com.ar/MLA-1969013848",
    "fecha": 1733107283606
  },
  {
    "url": "https://casa.mercadolibre.com.ar/MLA-1463571159",
    "fecha": 1733107281449
  },
  {
    "url": "https://casa.mercadolibre.com.ar/MLA-1463558967",
    "fecha": 1733107279950
  },
  {
    "url": "https://casa.mercadolibre.com.ar/MLA-1463371309",
    "fecha": 1733060200342
  },
  {
    "url": "https://inmueble.mercadolibre.com.ar/MLA-1463385331",
    "fecha": 1733060198485
  },
  {
    "url": "https://casa.mercadolibre.com.ar/MLA-1463448087",
    "fecha": 1733060196446
  },
  {
    "url": "https://departamento.mercadolibre.com.ar/MLA-1967269284",
    "fecha": 1732764481548
  },
  {
    "url": "https://inmueble.mercadolibre.com.ar/MLA-1967370292",
    "fecha": 1732764479369
  },
  {
    "url": "https://casa.mercadolibre.com.ar/MLA-1967294910",
    "fecha": 1732764477857
  },
  {
    "url": "https://departamento.mercadolibre.com.ar/MLA-1462902723",
    "fecha": 1732736022284
  },
  {
    "url": "https://terreno.mercadolibre.com.ar/MLA-1966788774",
    "fecha": 1732736020470
  },
  {
    "url": "https://departamento.mercadolibre.com.ar/MLA-1462836629",
    "fecha": 1732736018789
  },
  {
    "url": "https://terreno.mercadolibre.com.ar/MLA-1966507634",
    "fecha": 1732708977219
  },
  {
    "url": "https://departamento.mercadolibre.com.ar/MLA-1462744405",
    "fecha": 1732651799335
  },
  {
    "url": "https://terreno.mercadolibre.com.ar/MLA-1965957582",
    "fecha": 1732644501061
  },
  {
    "url": "https://departamento.mercadolibre.com.ar/MLA-1965940734",
    "fecha": 1732644499105
  },
  {
    "url": "https://terreno.mercadolibre.com.ar/MLA-1462567759",
    "fecha": 1732644497887
  },
  {
    "url": "https://casa.mercadolibre.com.ar/MLA-1965942804",
    "fecha": 1732644495331
  },
  {
    "url": "https://casa.mercadolibre.com.ar/MLA-1462569581",
    "fecha": 1732644493307
  },
  {
    "url": "https://departamento.mercadolibre.com.ar/MLA-1965927540",
    "fecha": 1732644491023
  },
  {
    "url": "https://casa.mercadolibre.com.ar/MLA-1462666905",
    "fecha": 1732644489894
  },
  {
    "url": "https://departamento.mercadolibre.com.ar/MLA-1965600012",
    "fecha": 1732579831457
  },
  {
    "url": "https://casa.mercadolibre.com.ar/MLA-1964883618",
    "fecha": 1732579829193
  },
  {
    "url": "https://casa.mercadolibre.com.ar/MLA-1964946270",
    "fecha": 1732579827387
  },
  {
    "url": "https://casa.mercadolibre.com.ar/MLA-1462483289",
    "fecha": 1732579825728
  },
  {
    "url": "https://departamento.mercadolibre.com.ar/MLA-1965052400",
    "fecha": 1732579822836
  },
  {
    "url": "https://departamento.mercadolibre.com.ar/MLA-1462472351",
    "fecha": 1732579821844
  },
  {
    "url": "https://terreno.mercadolibre.com.ar/MLA-1964883622",
    "fecha": 1732579820183
  },
  {
    "url": "https://terreno.mercadolibre.com.ar/MLA-1462405149",
    "fecha": 1732579817574
  },
  {
    "url": "https://casa.mercadolibre.com.ar/MLA-1964868396",
    "fecha": 1732495731011
  },
  {
    "url": "https://departamento.mercadolibre.com.ar/MLA-1462354483",
    "fecha": 1732461651450
  },
  {
    "url": "https://departamento.mercadolibre.com.ar/MLA-1462279951",
    "fecha": 1732461649813
  },
  {
    "url": "https://casa.mercadolibre.com.ar/MLA-1462278629",
    "fecha": 1732403178344
  },
  {
    "url": "https://casa.mercadolibre.com.ar/MLA-1964270810",
    "fecha": 1732383638190
  },
  {
    "url": "https://terreno.mercadolibre.com.ar/MLA-1462251947",
    "fecha": 1732383638177
  },
  {
    "url": "https://terreno.mercadolibre.com.ar/MLA-1462200177",
    "fecha": 1732383638055
  },
  {
    "url": "https://terreno.mercadolibre.com.ar/MLA-1964078668",
    "fecha": 1732383637674
  },
  {
    "url": "https://departamento.mercadolibre.com.ar/MLA-1964084556",
    "fecha": 1732383637559
  },
  {
    "url": "https://casa.mercadolibre.com.ar/MLA-1462063555",
    "fecha": 1732383637535
  },
  {
    "url": "https://casa.mercadolibre.com.ar/MLA-1462195559",
    "fecha": 1732383637531
  },
  {
    "url": "https://casa.mercadolibre.com.ar/MLA-1964064644",
    "fecha": 1732383637223
  },
  {
    "url": "https://casa.mercadolibre.com.ar/MLA-1462238783",
    "fecha": 1732383636896
  },
  {
    "url": "https://terreno.mercadolibre.com.ar/MLA-1963104320",
    "fecha": 1732222546177
  },
  {
    "url": "https://departamento.mercadolibre.com.ar/MLA-1461852161",
    "fecha": 1732222541342
  },
  {
    "url": "https://departamento.mercadolibre.com.ar/MLA-1963106820",
    "fecha": 1732222536478
  },
  {
    "url": "https://departamento.mercadolibre.com.ar/MLA-1963104316",
    "fecha": 1732222532051
  },
  {
    "url": "https://departamento.mercadolibre.com.ar/MLA-1963114886",
    "fecha": 1732222527500
  },
  {
    "url": "https://departamento.mercadolibre.com.ar/MLA-1962661608",
    "fecha": 1732222523015
  },
  {
    "url": "https://casa.mercadolibre.com.ar/MLA-1962679198",
    "fecha": 1732222517578
  },
  {
    "url": "https://casa.mercadolibre.com.ar/MLA-1461755153",
    "fecha": 1732159309947
  },
  {
    "url": "https://terreno.mercadolibre.com.ar/MLA-1962363718",
    "fecha": 1732159303390
  },
  {
    "url": "https://casa.mercadolibre.com.ar/MLA-1962389242",
    "fecha": 1732159296089
  },
  {
    "url": "https://casa.mercadolibre.com.ar/MLA-1962319826",
    "fecha": 1732159289625
  },
  {
    "url": "https://terreno.mercadolibre.com.ar/MLA-1962322786",
    "fecha": 1732159282925
  },
  {
    "url": "https://departamento.mercadolibre.com.ar/MLA-1962398798",
    "fecha": 1732159275459
  },
  {
    "url": "https://departamento.mercadolibre.com.ar/MLA-1962366852",
    "fecha": 1732159268974
  },
  {
    "url": "https://casa.mercadolibre.com.ar/MLA-1962365940",
    "fecha": 1732159262476
  },
  {
    "url": "https://departamento.mercadolibre.com.ar/MLA-1461698431",
    "fecha": 1732159254966
  },
  {
    "url": "https://casa.mercadolibre.com.ar/MLA-1962333052",
    "fecha": 1732159247687
  },
  {
    "url": "https://casa.mercadolibre.com.ar/MLA-1461618085",
    "fecha": 1732159240254
  },
  {
    "url": "https://casa.mercadolibre.com.ar/MLA-1461588063",
    "fecha": 1732119685617
  },
  {
    "url": "https://casa.mercadolibre.com.ar/MLA-1461649567",
    "fecha": 1732119679363
  },
  {
    "url": "https://departamento.mercadolibre.com.ar/MLA-1961341492",
    "fecha": 1732119672480
  },
  {
    "url": "https://casa.mercadolibre.com.ar/MLA-1961419122",
    "fecha": 1732119664843
  },
  {
    "url": "https://casa.mercadolibre.com.ar/MLA-1961353502",
    "fecha": 1732119657796
  }
]