[
  {
    "url": "https://departamento.mercadolibre.com.ar/MLA-1463474265",
    "fecha": 1733074024145
  },
  {
    "url": "https://departamento.mercadolibre.com.ar/MLA-1463451055",
    "fecha": 1733074021370
  },
  {
    "url": "https://departamento.mercadolibre.com.ar/MLA-1463442725",
    "fecha": 1733074019255
  },
  {
    "url": "https://departamento.mercadolibre.com.ar/MLA-1463442727",
    "fecha": 1733074017525
  },
  {
    "url": "https://departamento.mercadolibre.com.ar/MLA-1968794176",
    "fecha": 1733074015069
  },
  {
    "url": "https://departamento.mercadolibre.com.ar/MLA-1968805934",
    "fecha": 1733074013388
  },
  {
    "url": "https://casa.mercadolibre.com.ar/MLA-1968768380",
    "fecha": 1733074011704
  },
  {
    "url": "https://departamento.mercadolibre.com.ar/MLA-1968806058",
    "fecha": 1733074009373
  },
  {
    "url": "https://departamento.mercadolibre.com.ar/MLA-1968755326",
    "fecha": 1733074008103
  },
  {
    "url": "https://terreno.mercadolibre.com.ar/MLA-1463485651",
    "fecha": 1733074006351
  },
  {
    "url": "https://departamento.mercadolibre.com.ar/MLA-1968754724",
    "fecha": 1733074004259
  },
  {
    "url": "https://departamento.mercadolibre.com.ar/MLA-1966784522",
    "fecha": 1732722910611
  },
  {
    "url": "https://inmueble.mercadolibre.com.ar/MLA-1966773748",
    "fecha": 1732722908757
  },
  {
    "url": "https://inmueble.mercadolibre.com.ar/MLA-1966676296",
    "fecha": 1732722907316
  },
  {
    "url": "https://departamento.mercadolibre.com.ar/MLA-1462718793",
    "fecha": 1732722904754
  },
  {
    "url": "https://departamento.mercadolibre.com.ar/MLA-1462742389",
    "fecha": 1732722902776
  },
  {
    "url": "https://departamento.mercadolibre.com.ar/MLA-1966482422",
    "fecha": 1732722900736
  },
  {
    "url": "https://departamento.mercadolibre.com.ar/MLA-1966494454",
    "fecha": 1732722898422
  },
  {
    "url": "https://departamento.mercadolibre.com.ar/MLA-1462693711",
    "fecha": 1732722896802
  },
  {
    "url": "https://departamento.mercadolibre.com.ar/MLA-1966559104",
    "fecha": 1732722894426
  },
  {
    "url": "https://departamento.mercadolibre.com.ar/MLA-1966546026",
    "fecha": 1732722892409
  },
  {
    "url": "https://departamento.mercadolibre.com.ar/MLA-1966559108",
    "fecha": 1732722890366
  },
  {
    "url": "https://departamento.mercadolibre.com.ar/MLA-1966546022",
    "fecha": 1732722889044
  },
  {
    "url": "https://inmueble.mercadolibre.com.ar/MLA-1462765581",
    "fecha": 1732722886573
  },
  {
    "url": "https://inmueble.mercadolibre.com.ar/MLA-1462791583",
    "fecha": 1732722885299
  },
  {
    "url": "https://terreno.mercadolibre.com.ar/MLA-1966481000",
    "fecha": 1732722883487
  },
  {
    "url": "https://inmueble.mercadolibre.com.ar/MLA-1462818715",
    "fecha": 1732722880791
  },
  {
    "url": "https://inmueble.mercadolibre.com.ar/MLA-1966481572",
    "fecha": 1732722879460
  },
  {
    "url": "https://casa.mercadolibre.com.ar/MLA-1966533790",
    "fecha": 1732722877315
  },
  {
    "url": "https://casa.mercadolibre.com.ar/MLA-1966534986",
    "fecha": 1732722875384
  },
  {
    "url": "https://departamento.mercadolibre.com.ar/MLA-1964741270",
    "fecha": 1732480086359
  },
  {
    "url": "https://inmueble.mercadolibre.com.ar/MLA-1964626030",
    "fecha": 1732467474079
  },
  {
    "url": "https://departamento.mercadolibre.com.ar/MLA-1964576060",
    "fecha": 1732467471209
  },
  {
    "url": "https://departamento.mercadolibre.com.ar/MLA-1964638602",
    "fecha": 1732467469697
  },
  {
    "url": "https://departamento.mercadolibre.com.ar/MLA-1964550408",
    "fecha": 1732467467645
  },
  {
    "url": "https://casa.mercadolibre.com.ar/MLA-1964626052",
    "fecha": 1732467466027
  },
  {
    "url": "https://departamento.mercadolibre.com.ar/MLA-1462181591",
    "fecha": 1732395394500
  },
  {
    "url": "https://departamento.mercadolibre.com.ar/MLA-1462217233",
    "fecha": 1732395392213
  },
  {
    "url": "https://casa.mercadolibre.com.ar/MLA-1462235033",
    "fecha": 1732395390613
  },
  {
    "url": "https://inmueble.mercadolibre.com.ar/MLA-1964138002",
    "fecha": 1732395388388
  },
  {
    "url": "https://departamento.mercadolibre.com.ar/MLA-1964124892",
    "fecha": 1732395386554
  },
  {
    "url": "https://departamento.mercadolibre.com.ar/MLA-1964038976",
    "fecha": 1732395384975
  },
  {
    "url": "https://inmueble.mercadolibre.com.ar/MLA-1964140654",
    "fecha": 1732395383090
  },
  {
    "url": "https://inmueble.mercadolibre.com.ar/MLA-1461585169",
    "fecha": 1732144609715
  },
  {
    "url": "https://departamento.mercadolibre.com.ar/MLA-1461616589",
    "fecha": 1732144603265
  },
  {
    "url": "https://departamento.mercadolibre.com.ar/MLA-1961720340",
    "fecha": 1732144596731
  },
  {
    "url": "https://inmueble.mercadolibre.com.ar/MLA-1961769234",
    "fecha": 1732144590455
  },
  {
    "url": "https://departamento.mercadolibre.com.ar/MLA-1461657349",
    "fecha": 1732144584276
  },
  {
    "url": "https://departamento.mercadolibre.com.ar/MLA-1461662785",
    "fecha": 1732144577880
  },
  {
    "url": "https://casa.mercadolibre.com.ar/MLA-1961769872",
    "fecha": 1732144570732
  },
  {
    "url": "https://inmueble.mercadolibre.com.ar/MLA-1961706952",
    "fecha": 1732144563791
  },
  {
    "url": "https://inmueble.mercadolibre.com.ar/MLA-1461598945",
    "fecha": 1732144557395
  },
  {
    "url": "https://casa.mercadolibre.com.ar/MLA-1961776034",
    "fecha": 1732144550939
  },
  {
    "url": "https://terreno.mercadolibre.com.ar/MLA-1961776038",
    "fecha": 1732144544512
  },
  {
    "url": "https://inmueble.mercadolibre.com.ar/MLA-1961701876",
    "fecha": 1732144536580
  },
  {
    "url": "https://departamento.mercadolibre.com.ar/MLA-1461618081",
    "fecha": 1732144529137
  }
]