[
  {
    "url": "https://terreno.mercadolibre.com.ar/MLA-1463413321",
    "fecha": 1733074992067
  },
  {
    "url": "https://departamento.mercadolibre.com.ar/MLA-1462803873",
    "fecha": 1732724729521
  },
  {
    "url": "https://casa.mercadolibre.com.ar/MLA-1966651614",
    "fecha": 1732724727242
  },
  {
    "url": "https://departamento.mercadolibre.com.ar/MLA-1462705157",
    "fecha": 1732724725501
  },
  {
    "url": "https://casa.mercadolibre.com.ar/MLA-1462797009",
    "fecha": 1732724723030
  },
  {
    "url": "https://casa.mercadolibre.com.ar/MLA-1462693133",
    "fecha": 1732724721222
  },
  {
    "url": "https://casa.mercadolibre.com.ar/MLA-1966546182",
    "fecha": 1732724720119
  },
  {
    "url": "https://inmueble.mercadolibre.com.ar/MLA-1462319543",
    "fecha": 1732480504135
  },
  {
    "url": "https://terreno.mercadolibre.com.ar/MLA-1462239681",
    "fecha": 1732396535031
  },
  {
    "url": "https://inmueble.mercadolibre.com.ar/MLA-1462211473",
    "fecha": 1732396532704
  },
  {
    "url": "https://casa.mercadolibre.com.ar/MLA-1964271616",
    "fecha": 1732396530683
  },
  {
    "url": "https://casa.mercadolibre.com.ar/MLA-1964285888",
    "fecha": 1732396529074
  },
  {
    "url": "https://casa.mercadolibre.com.ar/MLA-1461526987",
    "fecha": 1732148973586
  },
  {
    "url": "https://terreno.mercadolibre.com.ar/MLA-1961702160",
    "fecha": 1732148967162
  }
]