[
  {
    "url": "https://departamento.mercadolibre.com.ar/MLA-1463536825",
    "fecha": 1733083083611
  },
  {
    "url": "https://departamento.mercadolibre.com.ar/MLA-1463464629",
    "fecha": 1733073846137
  },
  {
    "url": "https://terreno.mercadolibre.com.ar/MLA-1968579298",
    "fecha": 1733073845126
  },
  {
    "url": "https://departamento.mercadolibre.com.ar/MLA-1463451273",
    "fecha": 1733073841794
  },
  {
    "url": "https://departamento.mercadolibre.com.ar/MLA-1463464075",
    "fecha": 1733073839801
  },
  {
    "url": "https://departamento.mercadolibre.com.ar/MLA-1968686266",
    "fecha": 1733073838101
  },
  {
    "url": "https://departamento.mercadolibre.com.ar/MLA-1968686268",
    "fecha": 1733073835754
  },
  {
    "url": "https://departamento.mercadolibre.com.ar/MLA-1463451155",
    "fecha": 1733073834594
  },
  {
    "url": "https://departamento.mercadolibre.com.ar/MLA-1463451271",
    "fecha": 1733073832805
  },
  {
    "url": "https://departamento.mercadolibre.com.ar/MLA-1968754988",
    "fecha": 1733073831324
  },
  {
    "url": "https://terreno.mercadolibre.com.ar/MLA-1966788804",
    "fecha": 1732722553311
  },
  {
    "url": "https://departamento.mercadolibre.com.ar/MLA-1462859349",
    "fecha": 1732722550997
  },
  {
    "url": "https://inmueble.mercadolibre.com.ar/MLA-1462911515",
    "fecha": 1732722549473
  },
  {
    "url": "https://terreno.mercadolibre.com.ar/MLA-1966482468",
    "fecha": 1732722547294
  },
  {
    "url": "https://inmueble.mercadolibre.com.ar/MLA-1462793827",
    "fecha": 1732722545617
  },
  {
    "url": "https://departamento.mercadolibre.com.ar/MLA-1462778427",
    "fecha": 1732722542824
  },
  {
    "url": "https://departamento.mercadolibre.com.ar/MLA-1462703637",
    "fecha": 1732722540607
  },
  {
    "url": "https://departamento.mercadolibre.com.ar/MLA-1462796939",
    "fecha": 1732722538863
  },
  {
    "url": "https://departamento.mercadolibre.com.ar/MLA-1965880436",
    "fecha": 1732722536535
  },
  {
    "url": "https://departamento.mercadolibre.com.ar/MLA-1462729245",
    "fecha": 1732722534590
  },
  {
    "url": "https://departamento.mercadolibre.com.ar/MLA-1462795535",
    "fecha": 1732722532603
  },
  {
    "url": "https://departamento.mercadolibre.com.ar/MLA-1966278294",
    "fecha": 1732722530514
  },
  {
    "url": "https://departamento.mercadolibre.com.ar/MLA-1462730659",
    "fecha": 1732722528585
  },
  {
    "url": "https://departamento.mercadolibre.com.ar/MLA-1966275496",
    "fecha": 1732722526574
  },
  {
    "url": "https://departamento.mercadolibre.com.ar/MLA-1462782917",
    "fecha": 1732722524697
  },
  {
    "url": "https://departamento.mercadolibre.com.ar/MLA-1462692185",
    "fecha": 1732722522499
  },
  {
    "url": "https://departamento.mercadolibre.com.ar/MLA-1462770015",
    "fecha": 1732722520800
  },
  {
    "url": "https://departamento.mercadolibre.com.ar/MLA-1965944624",
    "fecha": 1732722518623
  },
  {
    "url": "https://departamento.mercadolibre.com.ar/MLA-1965918830",
    "fecha": 1732722516900
  },
  {
    "url": "https://departamento.mercadolibre.com.ar/MLA-1965867440",
    "fecha": 1732722514533
  },
  {
    "url": "https://departamento.mercadolibre.com.ar/MLA-1462715693",
    "fecha": 1732722512508
  },
  {
    "url": "https://departamento.mercadolibre.com.ar/MLA-1462767679",
    "fecha": 1732722510624
  },
  {
    "url": "https://departamento.mercadolibre.com.ar/MLA-1965905832",
    "fecha": 1732722508572
  },
  {
    "url": "https://departamento.mercadolibre.com.ar/MLA-1462702791",
    "fecha": 1732722506519
  },
  {
    "url": "https://departamento.mercadolibre.com.ar/MLA-1965971338",
    "fecha": 1732722504648
  },
  {
    "url": "https://casa.mercadolibre.com.ar/MLA-1462782237",
    "fecha": 1732722503726
  },
  {
    "url": "https://departamento.mercadolibre.com.ar/MLA-1966494778",
    "fecha": 1732722500835
  },
  {
    "url": "https://departamento.mercadolibre.com.ar/MLA-1966611288",
    "fecha": 1732722498756
  },
  {
    "url": "https://departamento.mercadolibre.com.ar/MLA-1462793737",
    "fecha": 1732722496841
  },
  {
    "url": "https://departamento.mercadolibre.com.ar/MLA-1462706791",
    "fecha": 1732722494847
  },
  {
    "url": "https://inmueble.mercadolibre.com.ar/MLA-1966494338",
    "fecha": 1732722492713
  },
  {
    "url": "https://terreno.mercadolibre.com.ar/MLA-1462703039",
    "fecha": 1732722491652
  },
  {
    "url": "https://inmueble.mercadolibre.com.ar/MLA-1966572374",
    "fecha": 1732722489292
  },
  {
    "url": "https://departamento.mercadolibre.com.ar/MLA-1965880216",
    "fecha": 1732722487006
  },
  {
    "url": "https://inmueble.mercadolibre.com.ar/MLA-1462801591",
    "fecha": 1732722485292
  },
  {
    "url": "https://departamento.mercadolibre.com.ar/MLA-1462791653",
    "fecha": 1732722483063
  },
  {
    "url": "https://departamento.mercadolibre.com.ar/MLA-1462757017",
    "fecha": 1732722481377
  },
  {
    "url": "https://terreno.mercadolibre.com.ar/MLA-1966478820",
    "fecha": 1732722479648
  },
  {
    "url": "https://departamento.mercadolibre.com.ar/MLA-1462722387",
    "fecha": 1732722477452
  },
  {
    "url": "https://inmueble.mercadolibre.com.ar/MLA-1966520560",
    "fecha": 1732722475658
  },
  {
    "url": "https://departamento.mercadolibre.com.ar/MLA-1964906238",
    "fecha": 1732497391397
  },
  {
    "url": "https://departamento.mercadolibre.com.ar/MLA-1462388481",
    "fecha": 1732490390587
  },
  {
    "url": "https://departamento.mercadolibre.com.ar/MLA-1462309423",
    "fecha": 1732487231621
  },
  {
    "url": "https://departamento.mercadolibre.com.ar/MLA-1462372357",
    "fecha": 1732487230128
  },
  {
    "url": "https://departamento.mercadolibre.com.ar/MLA-1462279981",
    "fecha": 1732467318200
  },
  {
    "url": "https://departamento.mercadolibre.com.ar/MLA-1964576044",
    "fecha": 1732467315781
  },
  {
    "url": "https://departamento.mercadolibre.com.ar/MLA-1462279983",
    "fecha": 1732467314534
  },
  {
    "url": "https://casa.mercadolibre.com.ar/MLA-1964550594",
    "fecha": 1732467312598
  },
  {
    "url": "https://departamento.mercadolibre.com.ar/MLA-1964562632",
    "fecha": 1732410103438
  },
  {
    "url": "https://departamento.mercadolibre.com.ar/MLA-1964599056",
    "fecha": 1732401603077
  },
  {
    "url": "https://departamento.mercadolibre.com.ar/MLA-1964636260",
    "fecha": 1732401601675
  },
  {
    "url": "https://departamento.mercadolibre.com.ar/MLA-1964052106",
    "fecha": 1732395179802
  },
  {
    "url": "https://inmueble.mercadolibre.com.ar/MLA-1964045560",
    "fecha": 1732395177367
  },
  {
    "url": "https://departamento.mercadolibre.com.ar/MLA-1964019972",
    "fecha": 1732395174924
  },
  {
    "url": "https://inmueble.mercadolibre.com.ar/MLA-1964115034",
    "fecha": 1732395173683
  },
  {
    "url": "https://departamento.mercadolibre.com.ar/MLA-1964086132",
    "fecha": 1732395170904
  },
  {
    "url": "https://departamento.mercadolibre.com.ar/MLA-1462220417",
    "fecha": 1732395169246
  },
  {
    "url": "https://departamento.mercadolibre.com.ar/MLA-1964019558",
    "fecha": 1732395166966
  },
  {
    "url": "https://departamento.mercadolibre.com.ar/MLA-1461602509",
    "fecha": 1732144012409
  },
  {
    "url": "https://departamento.mercadolibre.com.ar/MLA-1962384064",
    "fecha": 1732144005647
  },
  {
    "url": "https://departamento.mercadolibre.com.ar/MLA-1461629089",
    "fecha": 1732143999507
  },
  {
    "url": "https://departamento.mercadolibre.com.ar/MLA-1961744166",
    "fecha": 1732143992524
  },
  {
    "url": "https://departamento.mercadolibre.com.ar/MLA-1461610593",
    "fecha": 1732143985973
  },
  {
    "url": "https://departamento.mercadolibre.com.ar/MLA-1961845966",
    "fecha": 1732143979289
  },
  {
    "url": "https://departamento.mercadolibre.com.ar/MLA-1461685241",
    "fecha": 1732143972883
  },
  {
    "url": "https://departamento.mercadolibre.com.ar/MLA-1461624257",
    "fecha": 1732143966136
  },
  {
    "url": "https://departamento.mercadolibre.com.ar/MLA-1962323726",
    "fecha": 1732143959631
  },
  {
    "url": "https://departamento.mercadolibre.com.ar/MLA-1461644329",
    "fecha": 1732143952904
  },
  {
    "url": "https://inmueble.mercadolibre.com.ar/MLA-1961810724",
    "fecha": 1732143946184
  },
  {
    "url": "https://departamento.mercadolibre.com.ar/MLA-1461601351",
    "fecha": 1732143938714
  },
  {
    "url": "https://casa.mercadolibre.com.ar/MLA-1962359456",
    "fecha": 1732143932161
  },
  {
    "url": "https://terreno.mercadolibre.com.ar/MLA-1962359480",
    "fecha": 1732143925045
  },
  {
    "url": "https://departamento.mercadolibre.com.ar/MLA-1961712118",
    "fecha": 1732143917505
  }
]