[
  {
    "url": "https://casa.mercadolibre.com.ar/MLA-1463511299",
    "fecha": 1733082226748
  },
  {
    "url": "https://casa.mercadolibre.com.ar/MLA-1968843062",
    "fecha": 1733082224467
  },
  {
    "url": "https://casa.mercadolibre.com.ar/MLA-1968813976",
    "fecha": 1733071560562
  },
  {
    "url": "https://casa.mercadolibre.com.ar/MLA-1968807114",
    "fecha": 1733071558508
  },
  {
    "url": "https://casa.mercadolibre.com.ar/MLA-1967332166",
    "fecha": 1732756959610
  },
  {
    "url": "https://departamento.mercadolibre.com.ar/MLA-1462883531",
    "fecha": 1732756957980
  },
  {
    "url": "https://terreno.mercadolibre.com.ar/MLA-1967200924",
    "fecha": 1732756955780
  },
  {
    "url": "https://casa.mercadolibre.com.ar/MLA-1462918925",
    "fecha": 1732756954024
  },
  {
    "url": "https://casa.mercadolibre.com.ar/MLA-1966699366",
    "fecha": 1732719270998
  },
  {
    "url": "https://casa.mercadolibre.com.ar/MLA-1462897627",
    "fecha": 1732719269158
  },
  {
    "url": "https://casa.mercadolibre.com.ar/MLA-1966654440",
    "fecha": 1732719267275
  },
  {
    "url": "https://terreno.mercadolibre.com.ar/MLA-1966742560",
    "fecha": 1732719265552
  },
  {
    "url": "https://casa.mercadolibre.com.ar/MLA-1966481620",
    "fecha": 1732719263622
  },
  {
    "url": "https://terreno.mercadolibre.com.ar/MLA-1965969772",
    "fecha": 1732661095851
  },
  {
    "url": "https://casa.mercadolibre.com.ar/MLA-1965969792",
    "fecha": 1732661094019
  },
  {
    "url": "https://casa.mercadolibre.com.ar/MLA-1965963834",
    "fecha": 1732661091606
  },
  {
    "url": "https://terreno.mercadolibre.com.ar/MLA-1462697563",
    "fecha": 1732661089825
  },
  {
    "url": "https://casa.mercadolibre.com.ar/MLA-1965858974",
    "fecha": 1732661087514
  },
  {
    "url": "https://terreno.mercadolibre.com.ar/MLA-1462666883",
    "fecha": 1732661085502
  },
  {
    "url": "https://casa.mercadolibre.com.ar/MLA-1462789139",
    "fecha": 1732661084077
  },
  {
    "url": "https://casa.mercadolibre.com.ar/MLA-1462589903",
    "fecha": 1732661082632
  },
  {
    "url": "https://terreno.mercadolibre.com.ar/MLA-1462754783",
    "fecha": 1732661079282
  },
  {
    "url": "https://terreno.mercadolibre.com.ar/MLA-1462715833",
    "fecha": 1732661077872
  },
  {
    "url": "https://terreno.mercadolibre.com.ar/MLA-1462793747",
    "fecha": 1732661076299
  },
  {
    "url": "https://casa.mercadolibre.com.ar/MLA-1462615039",
    "fecha": 1732661074613
  },
  {
    "url": "https://casa.mercadolibre.com.ar/MLA-1462602423",
    "fecha": 1732661072256
  },
  {
    "url": "https://terreno.mercadolibre.com.ar/MLA-1462576417",
    "fecha": 1732661069995
  },
  {
    "url": "https://terreno.mercadolibre.com.ar/MLA-1462718143",
    "fecha": 1732661068499
  },
  {
    "url": "https://terreno.mercadolibre.com.ar/MLA-1964576194",
    "fecha": 1732465185377
  },
  {
    "url": "https://terreno.mercadolibre.com.ar/MLA-1462279907",
    "fecha": 1732465183485
  },
  {
    "url": "https://terreno.mercadolibre.com.ar/MLA-1964638800",
    "fecha": 1732465181422
  },
  {
    "url": "https://terreno.mercadolibre.com.ar/MLA-1964563436",
    "fecha": 1732465180152
  },
  {
    "url": "https://casa.mercadolibre.com.ar/MLA-1964576190",
    "fecha": 1732465177696
  },
  {
    "url": "https://terreno.mercadolibre.com.ar/MLA-1462292481",
    "fecha": 1732465176324
  },
  {
    "url": "https://terreno.mercadolibre.com.ar/MLA-1964547782",
    "fecha": 1732400779367
  },
  {
    "url": "https://casa.mercadolibre.com.ar/MLA-1964102518",
    "fecha": 1732392422774
  },
  {
    "url": "https://casa.mercadolibre.com.ar/MLA-1462211905",
    "fecha": 1732392420713
  },
  {
    "url": "https://terreno.mercadolibre.com.ar/MLA-1964060696",
    "fecha": 1732392419185
  },
  {
    "url": "https://casa.mercadolibre.com.ar/MLA-1461991759",
    "fecha": 1732237360143
  },
  {
    "url": "https://casa.mercadolibre.com.ar/MLA-1962721082",
    "fecha": 1732237355345
  },
  {
    "url": "https://casa.mercadolibre.com.ar/MLA-1962702928",
    "fecha": 1732237351107
  },
  {
    "url": "https://terreno.mercadolibre.com.ar/MLA-1962685466",
    "fecha": 1732237345703
  },
  {
    "url": "https://departamento.mercadolibre.com.ar/MLA-1461609037",
    "fecha": 1732133189191
  },
  {
    "url": "https://casa.mercadolibre.com.ar/MLA-1961766612",
    "fecha": 1732133181548
  }
]