[
  {
    "url": "https://casa.mercadolibre.com.ar/MLA-1968680538",
    "fecha": 1733060271109
  },
  {
    "url": "https://inmueble.mercadolibre.com.ar/MLA-1967313150",
    "fecha": 1732753930156
  },
  {
    "url": "https://inmueble.mercadolibre.com.ar/MLA-1462722691",
    "fecha": 1732651849738
  },
  {
    "url": "https://inmueble.mercadolibre.com.ar/MLA-1462545763",
    "fecha": 1732579952811
  },
  {
    "url": "https://inmueble.mercadolibre.com.ar/MLA-1965111422",
    "fecha": 1732579949664
  },
  {
    "url": "https://casa.mercadolibre.com.ar/MLA-1462214941",
    "fecha": 1732383723157
  },
  {
    "url": "https://departamento.mercadolibre.com.ar/MLA-1461895019",
    "fecha": 1732222671177
  },
  {
    "url": "https://casa.mercadolibre.com.ar/MLA-1962648318",
    "fecha": 1732222665849
  },
  {
    "url": "https://casa.mercadolibre.com.ar/MLA-1962364044",
    "fecha": 1732159487240
  },
  {
    "url": "https://casa.mercadolibre.com.ar/MLA-1461701271",
    "fecha": 1732159480453
  },
  {
    "url": "https://inmueble.mercadolibre.com.ar/MLA-1961821818",
    "fecha": 1732119848764
  }
]